LICENSE
README.md
setup.py
Resemblyzer_Ideas.egg-info/PKG-INFO
Resemblyzer_Ideas.egg-info/SOURCES.txt
Resemblyzer_Ideas.egg-info/dependency_links.txt
Resemblyzer_Ideas.egg-info/requires.txt
Resemblyzer_Ideas.egg-info/top_level.txt
resemblyzer/__init__.py
resemblyzer/audio.py
resemblyzer/hparams.py
resemblyzer/voice_encoder.py