Metadata-Version: 2.1
Name: Resemblyzer-Ideas
Version: 0.1.3
Summary: Analyze and compare voices with deep learning
Home-page: https://github.com/as-ideas/Resemblyzer
Author: Christian Schäfer (original repo Corentin Jemine)
Author-email: christian.schaefer@axelspringer.com
Classifier: Programming Language :: Python :: 3
Classifier: License :: OSI Approved :: Apache Software License
Classifier: Operating System :: OS Independent
Requires-Python: >=3.5
License-File: LICENSE
